{
  "monthly": [
    {
      "month": "March 2026",
      "monthShort": "Mar",
      "income": {
        "ote": 28689,
        "endorsement": 0,
        "additional": 1351,
        "vesperRidge": 0
      },
      "expenses": {
        "reimbursement": 0,
        "loanRepayment": 327.08,
        "creditCard": 2842.02,
        "other": 0,
        "taxes": 0,
        "personal1": 637.81,
        "personal2": 716.54
      }
    },
    {
      "month": "February 2026",
      "monthShort": "Feb",
      "income": {
        "ote": 21183,
        "endorsement": 0,
        "additional": 222,
        "vesperRidge": 0
      },
      "expenses": {
        "reimbursement": 0,
        "loanRepayment": 375.19,
        "creditCard": 5632.32,
        "other": 0,
        "taxes": 0,
        "personal1": 2715.89,
        "personal2": 105.6
      }
    },
    {
      "month": "January 2026",
      "monthShort": "Jan",
      "income": {
        "ote": 21187,
        "endorsement": 0,
        "additional": 111,
        "vesperRidge": 0
      },
      "expenses": {
        "reimbursement": 0,
        "loanRepayment": 0,
        "creditCard": 9837.11,
        "other": 0,
        "taxes": 0,
        "personal1": 5384.96,
        "personal2": 7152.2
      }
    },
    {
      "month": "December 2025",
      "monthShort": "Dec",
      "income": {
        "ote": 21190,
        "endorsement": 0,
        "additional": 111,
        "vesperRidge": 0
      },
      "expenses": {
        "reimbursement": 0,
        "loanRepayment": 0,
        "creditCard": 7166.14,
        "other": 0,
        "taxes": 0,
        "personal1": 1291.37,
        "personal2": 221.9
      }
    },
    {
      "month": "November 2025",
      "monthShort": "Nov",
      "income": {
        "ote": 20965,
        "endorsement": 0,
        "additional": 111,
        "vesperRidge": 0
      },
      "expenses": {
        "reimbursement": 0,
        "loanRepayment": 0,
        "creditCard": 6374.86,
        "other": 0,
        "taxes": 0,
        "personal1": 639.99,
        "personal2": 110.45
      }
    },
    {
      "month": "October 2025",
      "monthShort": "Oct",
      "income": {
        "ote": 21455,
        "endorsement": 0,
        "additional": 111,
        "vesperRidge": 0
      },
      "expenses": {
        "reimbursement": 0,
        "loanRepayment": 0,
        "creditCard": 6357.13,
        "other": 0,
        "taxes": 0,
        "personal1": 668.44,
        "personal2": 110.45
      }
    }
  ],
  "balance": [
    {
      "month": "Oct",
      "rothIra": 6414.85,
      "primaryLlc": 7865.84,
      "llcTaxReserve": 0,
      "investments": 1297843.07
    },
    {
      "month": "Nov",
      "rothIra": 6414.85,
      "primaryLlc": 19788.93,
      "llcTaxReserve": 0,
      "investments": 1297843.07
    },
    {
      "month": "Dec",
      "rothIra": 6024.48,
      "primaryLlc": 9429.82,
      "llcTaxReserve": 0,
      "investments": 0
    },
    {
      "month": "Jan",
      "rothIra": 6005.03,
      "primaryLlc": 16941.2,
      "llcTaxReserve": 0,
      "investments": 1172828.01
    },
    {
      "month": "Feb",
      "rothIra": 5284.16,
      "primaryLlc": 10124.53,
      "llcTaxReserve": 0,
      "investments": 1233509.35
    }
  ],
  "lastImport": "Apr 2 at 4:02 PM"
}